CHANGELOG
LICENSE
MANIFEST.in
README.rst
setup.py
apns_clerk/__init__.py
apns_clerk/apns.py
apns_clerk/certificate.py
apns_clerk/transport.py
apns_clerk.egg-info/PKG-INFO
apns_clerk.egg-info/SOURCES.txt
apns_clerk.egg-info/dependency_links.txt
apns_clerk.egg-info/requires.txt
apns_clerk.egg-info/top_level.txt
apns_clerk/backends/__init__.py
apns_clerk/backends/dummy.py
apns_clerk/backends/stdio.py
test/test.py
test/test_stdio.py