Metadata-Version: 1.1
Name: apns-clerk
Version: 0.1.2
Summary: Python client for Apple Push Notification service (APNs)
Home-page: https://bitbucket.org/aleksihoffman/apns-clerk
Author: Aleksi Hoffman
Author-email: aleksi@lekksi.com
License: Apache 2.0
Keywords: apns push notification apple messaging iOS
Platform: UNKNOWN
Classifier: Development Status :: 4 - Beta
Classifier: Intended Audience :: Developers
Classifier: License :: OSI Approved :: Apache Software License
Classifier: Programming Language :: Python
Classifier: Topic :: Software Development :: Libraries :: Python Modules
